{
  "exerciseId": "bike-40K-tt",
  "direction": "desc",
  "points": [
    {
      "value": 7178.7,
      "percentile": 1
    },
    {
      "value": 6981.3,
      "percentile": 5
    },
    {
      "value": 6848.41,
      "percentile": 10
    },
    {
      "value": 6703.22,
      "percentile": 20
    },
    {
      "value": 6599.56,
      "percentile": 30
    },
    {
      "value": 6527.6,
      "percentile": 40
    },
    {
      "value": 6459.85,
      "percentile": 50
    },
    {
      "value": 6395.76,
      "percentile": 60
    },
    {
      "value": 6315.31,
      "percentile": 70
    },
    {
      "value": 6221.66,
      "percentile": 80
    },
    {
      "value": 6101.35,
      "percentile": 90
    },
    {
      "value": 5991.47,
      "percentile": 95
    },
    {
      "value": 5849.16,
      "percentile": 99
    },
    {
      "value": 5720.86,
      "percentile": 99.9
    }
  ],
  "source": "Derived from FTP via power-to-speed model.",
  "confidence": "curated"
}