{
  "exerciseId": "l-sit-weighted",
  "direction": "asc",
  "points": [
    {
      "value": 0,
      "percentile": 1
    },
    {
      "value": 0,
      "percentile": 5
    },
    {
      "value": 0,
      "percentile": 10
    },
    {
      "value": 3,
      "percentile": 20
    },
    {
      "value": 6,
      "percentile": 30
    },
    {
      "value": 10,
      "percentile": 40
    },
    {
      "value": 15,
      "percentile": 50
    },
    {
      "value": 22,
      "percentile": 60
    },
    {
      "value": 30,
      "percentile": 70
    },
    {
      "value": 45,
      "percentile": 80
    },
    {
      "value": 65,
      "percentile": 90
    },
    {
      "value": 90,
      "percentile": 95
    },
    {
      "value": 150,
      "percentile": 99
    },
    {
      "value": 240,
      "percentile": 99.9
    }
  ],
  "source": "Curated L-sit hold times for healthy adults.",
  "confidence": "curated"
}